lisbon-0.1.0.dist-info/METADATA
lisbon-0.1.0.dist-info/WHEEL
lisbon/__init__.py
lisbon/lisbon.cpython-39-x86_64-linux-gnu.so
lisbon-0.1.0.dist-info/RECORD
